AncientLibrary/__init__.py
AncientLibrary/algebra.py
AncientLibrary/machine.py
AncientLibrary/solver.py
AncientLibrary/stats.py
AncientLibrary/visuals.py
AncientLibrary-0.0.5.dist-info/METADATA
AncientLibrary-0.0.5.dist-info/WHEEL
AncientLibrary-0.0.5.dist-info/top_level.txt
AncientLibrary-0.0.5.dist-info/RECORD
