Metadata-Version: 2.1
Name: AncientLibrary
Version: 0.0.5
Summary: Complete Data Science Package from Scratch
Home-page: https://github.com/cranialplating/AncientLibrary
Author: Ryan Holmes
Author-email: holmesforlan@gmail.com
License: UNKNOWN
Platform: UNKNOWN
Requires-Dist: numpy
Requires-Dist: matplotlib
